AnishModule/__init__.py
AnishModule/add.py
AnishModule-0.0.4.dist-info/METADATA
AnishModule-0.0.4.dist-info/WHEEL
AnishModule-0.0.4.dist-info/top_level.txt
AnishModule-0.0.4.dist-info/RECORD
