Metadata-Version: 2.1
Name: AnishModule
Version: 0.0.4
Summary: My first Python package -anish
Home-page: UNKNOWN
Author: Anish Miya 
Author-email: <anishmiyaie@gmail.com>
License: UNKNOWN
Keywords: python,first package
Platform: UNKNOWN
Classifier: Development Status :: 3 - Alpha
Classifier: Intended Audience :: Education
Classifier: Programming Language :: Python :: 2
Classifier: Programming Language :: Python :: 3
Classifier: Operating System :: MacOS :: MacOS X
Classifier: Operating System :: Microsoft :: Windows
